whichprovides/__init__.py
whichprovides/__main__.py
whichprovides-0.4.0.dist-info/METADATA
whichprovides-0.4.0.dist-info/WHEEL
whichprovides-0.4.0.dist-info/licenses/LICENSE
whichprovides-0.4.0.dist-info/RECORD
