Metadata-Version: 2.4
Name: whichprovides
Version: 0.4.0
Summary: Module which provides 'yum provides' functionality across many package managers
Project-URL: Home Page, https://codeberg.org/sethmlarson/whichprovides
Project-URL: Documentation, https://codeberg.org/sethmlarson/whichprovides
Project-URL: Source Code, https://codeberg.org/sethmlarson/whichprovides
License-Expression: MIT
License-File: LICENSE
Requires-Python: >=3.9
